{
	"configurations" : 
	[
		{
			"directories" : 
			[
				{
					"build" : ".",
					"jsonFile" : "directory-.-Debug-f5ebdc15457944623624.json",
					"minimumCMakeVersion" : 
					{
						"string" : "3.10"
					},
					"projectIndex" : 0,
					"source" : ".",
					"targetIndexes" : 
					[
						0
					]
				}
			],
			"name" : "Debug",
			"projects" : 
			[
				{
					"directoryIndexes" : 
					[
						0
					],
					"name" : "gkit2light",
					"targetIndexes" : 
					[
						0
					]
				}
			],
			"targets" : 
			[
				{
					"directoryIndex" : 0,
					"id" : "tuto7_camera::@6890427a1f51a3e7e1df",
					"jsonFile" : "target-tuto7_camera-Debug-1a79e4e45fee088bcdc8.json",
					"name" : "tuto7_camera",
					"projectIndex" : 0
				}
			]
		}
	],
	"kind" : "codemodel",
	"paths" : 
	{
		"build" : "/home/duskel/Documents/Github/gkit2light/build",
		"source" : "/home/duskel/Documents/Github/gkit2light"
	},
	"version" : 
	{
		"major" : 2,
		"minor" : 6
	}
}
